turing_machine_utils/__init__.py
turing_machine_utils/turing.py
turing_machine_utils-1.0.7.dist-info/LICENSE.md
turing_machine_utils-1.0.7.dist-info/METADATA
turing_machine_utils-1.0.7.dist-info/WHEEL
turing_machine_utils-1.0.7.dist-info/top_level.txt
turing_machine_utils-1.0.7.dist-info/RECORD
