Metadata-Version: 2.1
Name: turing-machine-utils
Version: 1.0.7
Summary: Calculate the result of a turing machine on a given tape
Home-page: https://github.com/porfanid/TuringMachine
Author: porfanid
Author-email: pavlos@orfanidis.net.gr
License: MIT
Project-URL: Funding, https://ko-fi.com/porfanid
Project-URL: Source, https://github.com/porfanid/TuringMachine
Project-URL: Documentation, https://github.com/porfanid/TuringMachine
Project-URL: Tracker, https://github.com/porfanid/TuringMachine/issues
Project-URL: Say Thanks!, https://saythanks.io/to/porfanid
Keywords: Turing Machine,Turing Machine Simulator,Python,Automata,Simulation,Computational Theory,State Machine,Algorithm,Artificial Intelligence,Machine Learning,Computational Science,Programming,Open Source,Education,Computer Science,Formal Languages,Computational Models,Tape,States,Transition Rules,Simulation Tool,Complexity,Symbol,Universal Turing Machine,Computer Engineering,Software Development
Platform: UNKNOWN
Requires-Python: >=3.6
Requires-Dist: markdown
